skoolkit-9.6.data/scripts/skool2bin.py
skoolkit-9.6.data/scripts/trace.py
skoolkit-9.6.data/scripts/rzxinfo.py
skoolkit-9.6.data/scripts/skool2ctl.py
skoolkit-9.6.data/scripts/bin2tap.py
skoolkit-9.6.data/scripts/sna2ctl.py
skoolkit-9.6.data/scripts/bin2sna.py
skoolkit-9.6.data/scripts/tap2sna.py
skoolkit-9.6.data/scripts/rzxplay.py
skoolkit-9.6.data/scripts/sna2img.py
skoolkit-9.6.data/scripts/skool2html.py
skoolkit-9.6.data/scripts/tapinfo.py
skoolkit-9.6.data/scripts/sna2skool.py
skoolkit-9.6.data/scripts/snapmod.py
skoolkit-9.6.data/scripts/snapinfo.py
skoolkit-9.6.data/scripts/skool2asm.py
skoolkit/loadtracer.py
skoolkit/screen.py
skoolkit/skool2bin.py
skoolkit/pngwriter.py
skoolkit/graphics.py
skoolkit/skoolasm.py
skoolkit/trace.py
skoolkit/skoolutils.py
skoolkit/traceutils.py
skoolkit/comment.py
skoolkit/simutils.py
skoolkit/config.py
skoolkit/opcodes.py
skoolkit/rzxinfo.py
skoolkit/ccmiosimulator.cpython-310-darwin.so
skoolkit/skool2ctl.py
skoolkit/refparser.py
skoolkit/bin2tap.py
skoolkit/disassembler.py
skoolkit/sna2ctl.py
skoolkit/kbtracer.py
skoolkit/tape.py
skoolkit/loadsample.py
skoolkit/textutils.py
skoolkit/bin2sna.py
skoolkit/__init__.py
skoolkit/skoolmacro.py
skoolkit/skoolparser.py
skoolkit/snaskool.py
skoolkit/skoolhtml.py
skoolkit/tap2sna.py
skoolkit/rzxplay.py
skoolkit/sna2img.py
skoolkit/skool2html.py
skoolkit/basic.py
skoolkit/simtables.py
skoolkit/cmiosimulator.py
skoolkit/pagingtracer.py
skoolkit/ctlparser.py
skoolkit/tapinfo.py
skoolkit/csimulator.cpython-310-darwin.so
skoolkit/simulator.py
skoolkit/defaults.py
skoolkit/audio.py
skoolkit/z80.py
skoolkit/sna2skool.py
skoolkit/components.py
skoolkit/snapmod.py
skoolkit/snapinfo.py
skoolkit/skoolctl.py
skoolkit/skool2asm.py
skoolkit/image.py
skoolkit/rst.py
skoolkit/snapshot.py
skoolkit/snactl.py
skoolkit/resources/128-1.rom
skoolkit/resources/128-0.rom
skoolkit/resources/skoolkit-plum.css
skoolkit-9.6.dist-info/RECORD
skoolkit-9.6.dist-info/WHEEL
skoolkit-9.6.dist-info/top_level.txt
skoolkit-9.6.dist-info/METADATA
skoolkit-9.6.dist-info/licenses/COPYING
