Metadata-Version: 2.4
Name: skoolkit
Version: 9.6
Summary: A suite of tools for creating disassemblies of ZX Spectrum games
Home-page: https://skoolkit.ca
Author: Richard Dymond
Author-email: rjdymond@gmail.com
License: GPLv3
Classifier: Development Status :: 5 - Production/Stable
Classifier: License :: OSI Approved :: GNU General Public License v3 or later (GPLv3+)
Classifier: Operating System :: OS Independent
Classifier: Programming Language :: Python :: 3
Classifier: Programming Language :: Python :: 3 :: Only
Classifier: Programming Language :: Python :: 3.9
Classifier: Programming Language :: Python :: 3.10
Classifier: Programming Language :: Python :: 3.11
Classifier: Programming Language :: Python :: 3.12
Classifier: Programming Language :: Python :: 3.13
Classifier: Topic :: Software Development :: Disassemblers
Classifier: Topic :: Utilities
License-File: COPYING
Dynamic: license-file
